fabric_cicd/__init__.py
fabric_cicd/changelog.md
fabric_cicd/constants.py
fabric_cicd/fabric_workspace.py
fabric_cicd/publish.py
fabric_cicd/_common/__init__.py
fabric_cicd/_common/_check_utils.py
fabric_cicd/_common/_color.py
fabric_cicd/_common/_config_utils.py
fabric_cicd/_common/_config_validator.py
fabric_cicd/_common/_exceptions.py
fabric_cicd/_common/_fabric_endpoint.py
fabric_cicd/_common/_file.py
fabric_cicd/_common/_item.py
fabric_cicd/_common/_logging.py
fabric_cicd/_common/_validate_input.py
fabric_cicd/_items/__init__.py
fabric_cicd/_items/_activator.py
fabric_cicd/_items/_apacheairflowjob.py
fabric_cicd/_items/_copyjob.py
fabric_cicd/_items/_dataagent.py
fabric_cicd/_items/_dataflowgen2.py
fabric_cicd/_items/_datapipeline.py
fabric_cicd/_items/_environment.py
fabric_cicd/_items/_eventhouse.py
fabric_cicd/_items/_eventstream.py
fabric_cicd/_items/_graphqlapi.py
fabric_cicd/_items/_kqldashboard.py
fabric_cicd/_items/_kqldatabase.py
fabric_cicd/_items/_kqlqueryset.py
fabric_cicd/_items/_lakehouse.py
fabric_cicd/_items/_manage_dependencies.py
fabric_cicd/_items/_mirroreddatabase.py
fabric_cicd/_items/_mlexperiment.py
fabric_cicd/_items/_mounteddatafactory.py
fabric_cicd/_items/_notebook.py
fabric_cicd/_items/_orgapp.py
fabric_cicd/_items/_report.py
fabric_cicd/_items/_semanticmodel.py
fabric_cicd/_items/_sparkjobdefinition.py
fabric_cicd/_items/_sqldatabase.py
fabric_cicd/_items/_userdatafunction.py
fabric_cicd/_items/_variablelibrary.py
fabric_cicd/_items/_warehouse.py
fabric_cicd/_parameter/__init__.py
fabric_cicd/_parameter/_parameter.py
fabric_cicd/_parameter/_utils.py
fabric_cicd-0.1.34.dist-info/licenses/LICENSE
fabric_cicd-0.1.34.dist-info/METADATA
fabric_cicd-0.1.34.dist-info/WHEEL
fabric_cicd-0.1.34.dist-info/top_level.txt
fabric_cicd-0.1.34.dist-info/RECORD
