Metadata-Version: 2.4
Name: fabric-cicd
Version: 0.1.34
Summary: Microsoft Fabric CI/CD
Author: Microsoft Corporation
License-Expression: MIT
Project-URL: Repository, https://github.com/microsoft/fabric-cicd.git
Classifier: Programming Language :: Python
Classifier: Programming Language :: Python :: 3.9
Classifier: Programming Language :: Python :: 3.10
Classifier: Programming Language :: Python :: 3.11
Classifier: Programming Language :: Python :: 3.12
Requires-Python: <3.13,>=3.9
License-File: LICENSE
Requires-Dist: azure-identity>=1.19.0
Requires-Dist: dpath>=2.2.0
Requires-Dist: filetype>=1.2.0
Requires-Dist: jsonpath-ng>=1.7.0
Requires-Dist: packaging>=24.2
Requires-Dist: pyyaml>=6.0.2
Requires-Dist: requests>=2.32.3
Dynamic: license-file
